[
  {
    "id": "8cb436c216f532de479c4087e3af84bb",
    "title": "CLB Thanh Hóa được FIFA xóa án sát giờ 'G'",
    "link": "https://tuoitre.vn/clb-thanh-hoa-duoc-fifa-xoa-an-sat-gio-g-20260316235330157.htm",
    "summary": "CLB Thanh Hóa đã hoàn tất nghĩa vụ tài chính, được FIFA gỡ lệnh cấm đăng ký cầu thủ mới.",
    "source": "Tuổi Trẻ",
    "category": "Tổng hợp",
    "published": "2026-03-17T03:28:45.992206+07:00",
    "fetched": "2026-03-17T03:28:45.992429+07:00"
  },
  {
    "id": "ef89df54131182ddc45e4ceda039b1a7",
    "title": "Mỹ giảm hơn 80% phí cho người từ bỏ quốc tịch, còn chỉ 450 USD",
    "link": "https://tuoitre.vn/my-giam-hon-80-phi-cho-nguoi-tu-bo-quoc-tich-con-chi-450-usd-20260316191145156.htm",
    "summary": "Chính phủ Mỹ sẽ giảm hơn 80% phí đối với người muốn từ bỏ quốc tịch, đưa mức phí từ 2.350 USD xuống còn 450 USD kể từ ngày 13-4.",
    "source": "Tuổi Trẻ",
    "category": "Tổng hợp",
    "published": "2026-03-17T01:49:10.948803+07:00",
    "fetched": "2026-03-17T01:49:10.948919+07:00"
  },
  {
    "id": "dd4709ae009800da5c4a7325dd74a0d3",
    "title": "Hết làm ngân hàng vẫn lừa 7 người chiếm đoạt hơn 9 tỉ đồng",
    "link": "https://tuoitre.vn/het-lam-ngan-hang-van-lua-7-nguoi-chiem-doat-hon-9-ti-dong-20260316190351679.htm",
    "summary": "Dù không còn làm trong ngân hàng, Nguyễn Việt Hưng vẫn lừa bảy khách hàng bằng hình thức vay tiền \"đáo hạn ngân hàng\".",
    "source": "Tuổi Trẻ",
    "category": "Tổng hợp",
    "published": "2026-03-17T01:49:10.948675+07:00",
    "fetched": "2026-03-17T01:49:10.948791+07:00"
  },
  {
    "id": "2c0606649e78fb4a04a7b949808cc249",
    "title": "Thủ tướng: Đề xuất thí điểm các cơ chế đặc thù, đột phá cho đặc khu Vân Đồn, Vân Phong, Phú Quốc",
    "link": "https://tuoitre.vn/thu-tuong-de-xuat-thi-diem-cac-co-che-dac-thu-dot-pha-cho-dac-khu-van-don-van-phong-phu-quoc-2026031618511408.htm",
    "summary": "Thủ tướng Phạm Minh Chính yêu cầu bám sát các kết luận, chỉ đạo để đề xuất thí điểm các cơ chế, chính sách đặc thù, đột phá, mang tính đòn bẩy, điểm tựa, bảo đảm trọng tâm, trọng điểm.",
    "source": "Tuổi Trẻ",
    "category": "Tổng hợp",
    "published": "2026-03-17T01:49:10.948554+07:00",
    "fetched": "2026-03-17T01:49:10.948664+07:00"
  },
  {
    "id": "b40740bb27c65288e2941b598a77cee3",
    "title": "Công an TP.HCM khởi tố người nuôi trái phép 66 gà lôi",
    "link": "https://tuoitre.vn/cong-an-tp-hcm-khoi-to-nguoi-nuoi-trai-phep-66-ga-loi-20260316194409216.htm",
    "summary": "Một người nuôi nhốt trái phép 49 con gà lôi trắng, 17 con gà lôi lam lưng trắng và một con trăn ở TPHCM đã bị khởi tố hình sự.",
    "source": "Tuổi Trẻ",
    "category": "Tổng hợp",
    "published": "2026-03-17T01:49:10.948432+07:00",
    "fetched": "2026-03-17T01:49:10.948542+07:00"
  },
  {
    "id": "75c63ac4968432fc89ce2e70f592a818",
    "title": "Chênh lệch giá vàng trong nước và thế giới lên đến 23,8 triệu đồng",
    "link": "https://tuoitre.vn/chenh-lech-gia-vang-trong-nuoc-va-the-gioi-len-den-23-8-trieu-dong-20260316195314499.htm",
    "summary": "Chiều nay, 16-3, giá vàng thế giới bất ngờ giảm mạnh từ 5.031 USD/ounce, có lúc chỉ còn 4.975 USD/ounce. Đến 19h30, giá vàng thế giới hồi phục nhẹ lên mức 5.021 USD/ounce.",
    "source": "Tuổi Trẻ",
    "category": "Tổng hợp",
    "published": "2026-03-17T01:49:10.948310+07:00",
    "fetched": "2026-03-17T01:49:10.948421+07:00"
  },
  {
    "id": "f1e22a9776295318a5814475602f00b5",
    "title": "Thủ tướng Phạm Minh Chính tiếp ba bộ trưởng Trung Quốc",
    "link": "https://tuoitre.vn/thu-tuong-pham-minh-chinh-tiep-ba-bo-truong-trung-quoc-20260316195531998.htm",
    "summary": "Chiều 16-3, tại trụ sở Chính phủ, Thủ tướng Phạm Minh Chính đã tiếp các Bộ trưởng Ngoại giao, Công an, Quốc phòng Trung Quốc.",
    "source": "Tuổi Trẻ",
    "category": "Tổng hợp",
    "published": "2026-03-17T01:49:10.948184+07:00",
    "fetched": "2026-03-17T01:49:10.948298+07:00"
  },
  {
    "id": "1b55bd83506dae2c09ddbb628f65ec5f",
    "title": "Nếu xung đột Trung Đông kéo dài, xem xét bố trí ngân sách hỗ trợ bình ổn giá xăng dầu",
    "link": "https://tuoitre.vn/neu-xung-dot-trung-dong-keo-dai-xem-xet-bo-tri-ngan-sach-ho-tro-binh-on-gia-xang-dau-20260316200953587.htm",
    "summary": "Chiều tối 16-3, Thủ tướng Phạm Minh Chính đã chủ trì cuộc họp Thường trực Chính phủ để tiếp tục cho ý kiến về các giải pháp bảo đảm cung ứng và bình ổn giá xăng dầu.",
    "source": "Tuổi Trẻ",
    "category": "Tổng hợp",
    "published": "2026-03-17T01:49:10.948039+07:00",
    "fetched": "2026-03-17T01:49:10.948172+07:00"
  },
  {
    "id": "faa1d8fc268c8e787205b07a995f13b7",
    "title": "Xiếc chính luận phục vụ nhiệm vụ chính trị đắt vé",
    "link": "https://tuoitre.vn/xiec-chinh-luan-phuc-vu-nhiem-vu-chinh-tri-dat-ve-20260316192611753.htm",
    "summary": "Hàng loạt chương trình xiếc chính luận của Liên đoàn Xiếc Việt Nam kỷ niệm các ngày lễ lớn như Ngày thành lập Đảng, thành lập Đoàn, Ngày thống nhất đất nước, sinh nhật Bác Hồ, Ngày Quốc khánh... thời gian qua đều đắt vé.",
    "source": "Tuổi Trẻ",
    "category": "Tổng hợp",
    "published": "2026-03-17T01:49:10.947911+07:00",
    "fetched": "2026-03-17T01:49:10.948023+07:00"
  },
  {
    "id": "bf2780a261b48901414e4b8d03f762f1",
    "title": "Tìm thân nhân bé sơ sinh bị bỏ rơi dưới hầm chui cao tốc Vũng Áng - Bùng",
    "link": "https://tuoitre.vn/tim-than-nhan-be-so-sinh-bi-bo-roi-duoi-ham-chui-cao-toc-vung-ang-bung-20260316204139676.htm",
    "summary": "Một bé sơ sinh chỉ khoảng vài ngày tuổi bị bỏ rơi dưới hầm chui cao tốc đoạn Vũng Áng - Bùng. Chính quyền xã Nam Gianh đã phát thông báo tìm thân nhân cho cháu bé.",
    "source": "Tuổi Trẻ",
    "category": "Tổng hợp",
    "published": "2026-03-17T01:49:10.947787+07:00",
    "fetched": "2026-03-17T01:49:10.947900+07:00"
  },
  {
    "id": "d095af520707a7b7c971878be626c3f2",
    "title": "SCB sắp đấu giá loạt bất động sản, ô tô, túi xách... liên quan bà Trương Mỹ Lan",
    "link": "https://tuoitre.vn/scb-sap-dau-gia-loat-bat-dong-san-o-to-tui-xach-lien-quan-ba-truong-my-lan-20260316210923887.htm",
    "summary": "SCB đang tìm đơn vị tư vấn đấu thầu để xử lý 12 tài sản bảo đảm liên quan bà Trương Mỹ Lan, gồm bất động sản, ô tô, quần áo, túi xách…",
    "source": "Tuổi Trẻ",
    "category": "Tổng hợp",
    "published": "2026-03-17T01:49:10.947648+07:00",
    "fetched": "2026-03-17T01:49:10.947775+07:00"
  },
  {
    "id": "bb3a97222900d47c74c986004876e720",
    "title": "Washington nói thượng đỉnh Mỹ - Trung có thể bị hoãn nhưng không hủy",
    "link": "https://tuoitre.vn/washington-noi-thuong-dinh-my-trung-co-the-bi-hoan-nhung-khong-huy-20260316213610019.htm",
    "summary": "Phía Mỹ cho biết thượng đỉnh Mỹ - Trung có thể bị hoãn vì ông Trump cần ở lại Washington để điều phối cuộc chiến tại Iran.",
    "source": "Tuổi Trẻ",
    "category": "Tổng hợp",
    "published": "2026-03-17T01:49:10.947523+07:00",
    "fetched": "2026-03-17T01:49:10.947636+07:00"
  },
  {
    "id": "02d040f43f0bcee6555d2b809d969e3c",
    "title": "Thông tuyến đường sắt qua đèo Hải Vân sau sự cố đá lăn",
    "link": "https://tuoitre.vn/thong-tuyen-duong-sat-qua-deo-hai-van-sau-su-co-da-lan-20260316214603975.htm",
    "summary": "Tuyến đường sắt qua đèo Hải Vân - nối Đà Nẵng với Huế - đã thông tuyến trở lại sau hai ngày gián đoạn do sự cố đá lăn.",
    "source": "Tuổi Trẻ",
    "category": "Tổng hợp",
    "published": "2026-03-17T01:49:10.947397+07:00",
    "fetched": "2026-03-17T01:49:10.947511+07:00"
  },
  {
    "id": "09e4330dc8c83872f97afd6b1d4d0572",
    "title": "Người Cuba ở nước ngoài được phép đầu tư, sở hữu doanh nghiệp trong nước",
    "link": "https://tuoitre.vn/nguoi-cuba-o-nuoc-ngoai-duoc-phep-dau-tu-so-huu-doanh-nghiep-trong-nuoc-20260316220130117.htm",
    "summary": "Đây là thông tin được Phó thủ tướng kiêm Bộ trưởng Ngoại thương Cuba Oscar Perez-Oliva Fraga chia sẻ ngày 16-3.",
    "source": "Tuổi Trẻ",
    "category": "Tổng hợp",
    "published": "2026-03-17T01:49:10.947265+07:00",
    "fetched": "2026-03-17T01:49:10.947385+07:00"
  },
  {
    "id": "ba68ac9fff942888232f64c986b7a75d",
    "title": "Kịp thời cứu nam thanh niên nhảy cầu Bính",
    "link": "https://tuoitre.vn/kip-thoi-cuu-nam-thanh-nien-nhay-cau-binh-20260316221109034.htm",
    "summary": "Công an phường Thủy Nguyên phối hợp với Hải đội 4 - Bộ Tư lệnh Hải quân Vùng 1 kịp thời cứu nam thanh niên nhảy cầu Bính.",
    "source": "Tuổi Trẻ",
    "category": "Tổng hợp",
    "published": "2026-03-17T01:49:10.947102+07:00",
    "fetched": "2026-03-17T01:49:10.947250+07:00"
  },
  {
    "id": "604c39d9b65a981ac7447778b427f439",
    "title": "Thủ tướng Phạm Minh Chính điện đàm với Tổng thống Angola, đề nghị hỗ trợ thêm dầu thô và khí đốt",
    "link": "https://tuoitre.vn/thu-tuong-pham-minh-chinh-dien-dam-voi-tong-thong-angola-de-nghi-ho-tro-them-dau-tho-va-khi-dot-20260316224735643.htm",
    "summary": "Tổng thống Angola nhất trí đẩy mạnh hợp tác năng lượng giữa hai nước như Thủ tướng Phạm Minh Chính đề nghị.",
    "source": "Tuổi Trẻ",
    "category": "Tổng hợp",
    "published": "2026-03-17T01:49:10.946864+07:00",
    "fetched": "2026-03-17T01:49:10.947087+07:00"
  },
  {
    "id": "91b437d163c4391e9cda57d1c7f54cc4",
    "title": "Tàu hỏa tông văng ôtô 5 chỗ xuống mương nước ở Hà Nội",
    "link": "https://vnexpress.net/tau-hoa-tong-vang-oto-5-cho-xuong-muong-nuoc-o-ha-noi-5051222.html",
    "summary": "Ôtô 5 chỗ băng qua lối đi dân sinh cắt ngang đường sắt ở xã Đại Thanh, đúng lúc tàu chở hàng số hiệu 3606 tông vào đuôi, hất văng xuống mương nước, tài xế may mắn thoát nạn, tối 16/3.",
    "source": "VnExpress",
    "category": "Tổng hợp",
    "published": "2026-03-16T18:00:49+07:00",
    "fetched": "2026-03-17T03:28:42.166345+07:00"
  },
  {
    "id": "c9dd70a86b38d22f8c50db35e21d9475",
    "title": "Kíp tên lửa Iran trong cuộc đối đầu sinh tử với Mỹ - Israel",
    "link": "https://vnexpress.net/kip-ten-lua-iran-trong-cuoc-doi-dau-sinh-tu-voi-my-israel-5049804.html",
    "summary": "Tên lửa đạn đạo là trọng tâm trong chiến dịch trả đũa của Iran, khiến các kíp vận hành là mục tiêu săn lùng hàng đầu của Mỹ - Israel.",
    "source": "VnExpress - Thế Giới",
    "category": "Thế giới",
    "published": "2026-03-16T18:00:00+07:00",
    "fetched": "2026-03-17T01:49:12.147905+07:00"
  },
  {
    "id": "4aba5c846e672d287b8ee456347c084e",
    "title": "Dấu hiệu cảnh báo cơ thể thiếu canxi",
    "link": "https://vnexpress.net/dau-hieu-canh-bao-co-the-thieu-canxi-5051062.html",
    "summary": "Nồng độ canxi trong máu thấp có thể gây ra các triệu chứng thiếu canxi như đau cơ, chuột rút, da khô, giảm mật độ xương và mệt mỏi.",
    "source": "VnExpress",
    "category": "Tổng hợp",
    "published": "2026-03-16T18:00:00+07:00",
    "fetched": "2026-03-17T03:28:42.166560+07:00"
  },
  {
    "id": "48a61c78ed87bc980d6d4248c3881ad6",
    "title": "Rủi ro khi đầu tư mô hình 'phân lô bán nền' đất nông nghiệp",
    "link": "https://vnexpress.net/rui-ro-khi-dau-tu-mo-hinh-phan-lo-ban-nen-dat-nong-nghiep-5048674.html",
    "summary": "Đầu tư đất nông nghiệp rồi chia nhỏ bán cho nhiều người tiềm ẩn rủi ro pháp lý, dễ phát sinh tranh chấp, thậm chí mất trắng tài sản, theo chuyên gia.",
    "source": "VnExpress",
    "category": "Tổng hợp",
    "published": "2026-03-16T18:00:00+07:00",
    "fetched": "2026-03-17T03:28:42.166898+07:00"
  },
  {
    "id": "f68720da7138ffb714477719f31caf7f",
    "title": "Thủ đoạn dụ dỗ thiếu nữ đến trang trại biệt lập của 'tỷ phú ấu dâm'",
    "link": "https://vnexpress.net/thu-doan-du-do-thieu-nu-den-trang-trai-biet-lap-cua-ty-phu-au-dam-5051212.html",
    "summary": "Trang trại Zorro hơn 4.000 ha của tỷ phú Jeffrey Epstein được ví như thiên đường giữa sa mạc, nhưng bên trong dinh thự xa hoa là mạng lưới lạm dụng tình dục kéo dài nhiều thập kỷ.",
    "source": "VnExpress",
    "category": "Tổng hợp",
    "published": "2026-03-16T17:24:35+07:00",
    "fetched": "2026-03-17T01:49:06.770297+07:00"
  },
  {
    "id": "f53c7a81ad8d994fc0c74b448320efd4",
    "title": "Ngày mới với tin tức sức khỏe: Đậu phộng, đi bộ và cà phê - những phát hiện đáng chú ý",
    "link": "https://thanhnien.vn/ngay-moi-voi-tin-tuc-suc-khoe-dau-phong-di-bo-va-ca-phe-nhung-phat-hien-dang-chu-y-18526031623405565.htm",
    "summary": "Ngày mới với tin tức sức khỏe sẽ cùng điểm qua một số thông tin sức khỏe đáng chú ý liên quan đến chế độ ăn uống và vận động hằng ngày.",
    "source": "Thanh Niên",
    "category": "Tổng hợp",
    "published": "2026-03-16T17:10:00+07:00",
    "fetched": "2026-03-17T01:49:09.871896+07:00"
  },
  {
    "id": "20662f41199a9d49c348f476bade4966",
    "title": "Đậu phộng luộc hay rang: cách chế biến nào tốt cho sức khỏe hơn?",
    "link": "https://thanhnien.vn/dau-phong-luoc-hay-rang-cach-che-bien-nao-tot-cho-suc-khoe-hon-185260316181149879.htm",
    "summary": "Hai cách chế biến đậu phộng phổ biến nhất là luộc và rang. Mỗi phương pháp có thể làm thay đổi thành phần dinh dưỡng, hương vị và lượng calo trong đậu.",
    "source": "Thanh Niên",
    "category": "Tổng hợp",
    "published": "2026-03-16T17:09:00+07:00",
    "fetched": "2026-03-17T01:49:09.872060+07:00"
  },
  {
    "id": "4bdcd1985c9c380dfdd48469bbd11fc8",
    "title": "Nghiên cứu tìm ra số tách cà phê lý tưởng cho người lớn tuổi",
    "link": "https://thanhnien.vn/nghien-cuu-tim-ra-so-tach-ca-phe-ly-tuong-cho-nguoi-lon-tuoi-185260316212249702.htm",
    "summary": "Cà phê không chỉ giúp tăng sự tỉnh táo và năng lượng mà còn được cho là góp phần kéo dài tuổi thọ nhờ khả năng giảm nguy cơ suy tim, đột quỵ, tiểu đường, thậm chí một số loại ung thư.",
    "source": "Thanh Niên",
    "category": "Tổng hợp",
    "published": "2026-03-16T17:08:00+07:00",
    "fetched": "2026-03-17T01:49:09.872236+07:00"
  },
  {
    "id": "be8773a3f56d12de30344c96eea0b8d2",
    "title": "Mở rộng không gian căn hộ 73,5 m2 bằng tường vách kính",
    "link": "https://vnexpress.net/mo-rong-khong-gian-can-ho-73-5-m2-bang-tuong-vach-kinh-5050687.html",
    "summary": "Hệ vách kính di động thay thế tường cố định, giúp gia chủ dễ dàng chuyển đổi không gian sinh hoạt chung thành phòng làm việc riêng tư.",
    "source": "VnExpress",
    "category": "Tổng hợp",
    "published": "2026-03-16T17:05:00+07:00",
    "fetched": "2026-03-17T01:49:06.770482+07:00"
  },
  {
    "id": "dd78759bb93e4b8f0a6d4015d249d5db",
    "title": "Vì sao xuất tinh nhưng không đạt cực khoái?",
    "link": "https://vnexpress.net/vi-sao-xuat-tinh-nhung-khong-dat-cuc-khoai-5050622.html",
    "summary": "Dù quá trình xuất tinh vẫn diễn ra bình thường, nhiều nam giới lại đánh mất hoàn toàn cảm giác thăng hoa do ảnh hưởng từ bệnh lý nền, tác dụng phụ của thuốc hoặc áp lực tâm lý kéo dài.",
    "source": "VnExpress",
    "category": "Tổng hợp",
    "published": "2026-03-16T17:04:00+07:00",
    "fetched": "2026-03-17T01:49:06.770657+07:00"
  },
  {
    "id": "7b55c3febe6432722c5d293ef1fabad3",
    "title": "7 loại rau củ dùng thường xuyên tốt cho gan ruột",
    "link": "https://vnexpress.net/7-loai-rau-cu-dung-thuong-xuyen-tot-cho-gan-ruot-5050439.html",
    "summary": "Ăn súp lơ trắng, bông cải xanh có thể kích hoạt enzyme gan giúp đào thải độc tố, còn mướp đắng, khoai lang giàu chất xơ hỗ trợ tiêu hóa.",
    "source": "VnExpress",
    "category": "Tổng hợp",
    "published": "2026-03-16T17:04:00+07:00",
    "fetched": "2026-03-17T01:49:06.770819+07:00"
  },
  {
    "id": "7353f28ed979a554b2097f605a3b4582",
    "title": "4 con giáp càng về trung niên càng giàu có",
    "link": "https://vnexpress.net/van-may-12-con-giap-con-giap-may-man-hom-nay-4-con-giap-cang-ve-trung-nien-cang-giau-co-5051109.html",
    "summary": "Đối với một số con giáp, tuổi 40 giống như cột mốc đánh dấu bước ngoặt lớn trong cuộc đời.",
    "source": "VnExpress",
    "category": "Tổng hợp",
    "published": "2026-03-16T17:02:00+07:00",
    "fetched": "2026-03-17T01:49:06.770977+07:00"
  },
  {
    "id": "a0d5a89c9fb9c59e6953275e7211b193",
    "title": "Thiết kế nhà ga VIP sân bay Phú Quốc tái hiện vẻ đẹp biển đảo",
    "link": "https://vnexpress.net/thiet-ke-nha-ga-vip-san-bay-phu-quoc-tai-hien-ve-dep-bien-dao-5051205.html",
    "summary": "Nhà ga VIP sân bay Phú Quốc được thiết kế với hình dáng uyển chuyển của cá đại bàng biển, bên trong là chuỗi không gian gợi hành trình khám phá đại dương.",
    "source": "VnExpress",
    "category": "Tổng hợp",
    "published": "2026-03-16T17:00:00+07:00",
    "fetched": "2026-03-17T01:49:06.771154+07:00"
  },
  {
    "id": "aea42d0cb74a98c7273f4acd6ecf2fa7",
    "title": "Đột nhập căn hộ của người quen trộm 5,3 cây vàng",
    "link": "https://vnexpress.net/dot-nhap-can-ho-cua-nguoi-quen-trom-5-3-cay-vang-5051199.html",
    "summary": "Nhân lúc nhà họ hàng về quê ăn Tết, Nguyễn Gia Huy, 16 tuổi, dùng máy cắt sắt cạy cửa chính căn hộ chung cư, đột nhập, phá két sắt trộm 5,3 cây vàng.",
    "source": "VnExpress",
    "category": "Tổng hợp",
    "published": "2026-03-16T17:00:00+07:00",
    "fetched": "2026-03-17T01:49:06.771316+07:00"
  },
  {
    "id": "0110e9ad845e9cd1df48892a867e699d",
    "title": "Chủ nhà tự ý mở cửa vào xem khách thuê 'ăn ở ra sao', có phạm luật không?",
    "link": "https://vnexpress.net/chu-nha-tu-y-mo-cua-vao-xem-khach-thue-an-o-ra-sao-co-pham-luat-khong-5051194.html",
    "summary": "Gia đình tôi thuê nguyên căn chung cư theo hợp đồng một năm, nhưng không có điều khoản cụ thể về việc chủ nhà có được vào nhà khi người thuê vắng mặt hay không.",
    "source": "VnExpress",
    "category": "Tổng hợp",
    "published": "2026-03-16T17:00:00+07:00",
    "fetched": "2026-03-17T01:49:06.771480+07:00"
  },
  {
    "id": "fefa88bad424f7f92783d75d7dd3f315",
    "title": "Quyết định đáng giá khi tôi bán nhà mặt đất 3,2 tỷ mua hai căn chung cư",
    "link": "https://vnexpress.net/quyet-dinh-dang-gia-khi-toi-ban-nha-mat-dat-3-2-ty-mua-hai-can-chung-cu-5051133.html",
    "summary": "Bỏ ngoài tai những lời khuyên can, tôi quyết bán nhà mặt đất 3,2 tỷ, bỏ thêm 400 triệu mua hai căn chung cư rồi đưa cả nhà lên đó.",
    "source": "VnExpress",
    "category": "Tổng hợp",
    "published": "2026-03-16T17:00:00+07:00",
    "fetched": "2026-03-17T01:49:06.771633+07:00"
  },
  {
    "id": "12652abc04c9dc2ab7aef4ad60737050",
    "title": "Vợ chồng chọn nơi sống tiện công việc hay thuận lợi chăm con",
    "link": "https://vnexpress.net/vo-chong-chon-noi-song-tien-cong-viec-hay-thuan-loi-cham-con-5051106.html",
    "summary": "Vợ chồng có một nhà ở quê, một ở thành phố thuộc tỉnh; ở quê gần con, tiện chăm sóc, lên thành phố môi trường học tốt hơn.",
    "source": "VnExpress",
    "category": "Tổng hợp",
    "published": "2026-03-16T17:00:00+07:00",
    "fetched": "2026-03-17T01:49:06.771784+07:00"
  },
  {
    "id": "ba125b5a99c73ba3e445cfdf633b5ac3",
    "title": "Hàn Quốc dự kiến cấp visa 10 năm cho du khách Việt",
    "link": "https://vnexpress.net/han-quoc-du-kien-cap-visa-10-nam-cho-du-khach-viet-5051097.html",
    "summary": "Hàn Quốc dự kiến cấp visa nhập cảnh nhiều lần thời hạn 10 năm cho du khách từ các thành phố lớn của Việt Nam và Trung Quốc nhằm thúc đẩy du lịch.",
    "source": "VnExpress",
    "category": "Tổng hợp",
    "published": "2026-03-16T17:00:00+07:00",
    "fetched": "2026-03-17T01:49:06.771945+07:00"
  },
  {
    "id": "d78d6098174dc93d3836eca212642b85",
    "title": "Phạt 2 tỷ đồng nếu để xảy ra sự cố hạt nhân",
    "link": "https://vnexpress.net/phat-2-ty-dong-neu-de-xay-ra-su-co-hat-nhan-5051035.html",
    "summary": "Chính phủ quy định mức phạt hành chính cao nhất 2 tỷ đồng đối với hành vi không thực hiện các biện pháp ngăn ngừa để xảy ra sự cố tại nhà máy điện hạt nhân.",
    "source": "VnExpress",
    "category": "Tổng hợp",
    "published": "2026-03-16T17:00:00+07:00",
    "fetched": "2026-03-17T01:49:06.772106+07:00"
  },
  {
    "id": "45f4e4d239bf189c07fefd46bb00063b",
    "title": "6 năm 'yêu không cần cưới' của Lệ Quyên, Lâm Bảo Châu",
    "link": "https://vnexpress.net/6-nam-yeu-khong-can-cuoi-cua-le-quyen-lam-bao-chau-5050920.html",
    "summary": "Ca sĩ Lệ Quyên cho biết gắn bó Lâm Bảo Châu bằng sự thấu hiểu, xem sáu năm qua là chặng đường bình yên sau một lần đổ vỡ.",
    "source": "VnExpress",
    "category": "Tổng hợp",
    "published": "2026-03-16T17:00:00+07:00",
    "fetched": "2026-03-17T01:49:06.772291+07:00"
  },
  {
    "id": "05316eb8b78639191e5e31c5cb43f97c",
    "title": "Logistics 'thời chiến'",
    "link": "https://vnexpress.net/logistics-thoi-chien-5050674.html",
    "summary": "Khi giá dầu tăng gần 36%, các nhà cung cấp vận tải đường bộ của công ty tôi tạm dừng nhận đơn hàng vì \"không mua được dầu\".",
    "source": "VnExpress",
    "category": "Tổng hợp",
    "published": "2026-03-16T17:00:00+07:00",
    "fetched": "2026-03-17T01:49:06.772452+07:00"
  },
  {
    "id": "a50454e4bb7ef38dea6441c1e93d4b10",
    "title": "Chuyến hộ tống tàu dầu từng khiến hải quân Mỹ 'mất mặt' trên Vịnh Ba Tư",
    "link": "https://vnexpress.net/chuyen-ho-tong-tau-dau-tung-khien-hai-quan-my-mat-mat-tren-vinh-ba-tu-5049759.html",
    "summary": "Mỹ từng mở chiến dịch hộ tống tàu dầu qua Eo biển Hormuz năm 1987, nhưng sự cố siêu tàu Bridgeton trúng thủy lôi đã giáng đòn vào hình ảnh hải quân nước này.",
    "source": "VnExpress",
    "category": "Tổng hợp",
    "published": "2026-03-16T17:00:00+07:00",
    "fetched": "2026-03-17T01:49:06.772610+07:00"
  },
  {
    "id": "aa40d159404e2cded7856b0a28469990",
    "title": "Đội tuyển Việt Nam quyết thắng Malaysia bằng diện mạo mới",
    "link": "https://thanhnien.vn/doi-tuyen-viet-nam-quyet-thang-malaysia-bang-dien-mao-moi-185260316211240795.htm",
    "summary": "Trước cuộc tái đấu Malaysia tại lượt cuối vòng loại Asian Cup 2027, đội tuyển VN được kỳ vọng sẽ xuất hiện với diện mạo mới, đặc biệt ở hàng phòng ngự, bởi nhiều gương mặt quen thuộc đang trở lại đúng thời điểm. Nếu những nhân tố này tỏa sáng, VN đủ sức giành chiến thắng thuyết phục.",
    "source": "Thanh Niên",
    "category": "Tổng hợp",
    "published": "2026-03-16T17:00:00+07:00",
    "fetched": "2026-03-17T01:49:09.872393+07:00"
  },
  {
    "id": "87860eea0f3237dcc1ffb6719d38ae2e",
    "title": "Vòng tứ kết hứa hẹn bất ngờ thú vị",
    "link": "https://thanhnien.vn/vong-tu-ket-hua-hen-bat-ngo-thu-vi-185260316204724947.htm",
    "summary": "Hôm nay 17.3, trên sân Trường ĐH Nha Trang (Khánh Hòa) diễn ra 2 cặp tứ kết đầu tiên của vòng chung kết giải bóng đá Thanh Niên sinh viên VN lần IV - 2026 cúp THACO (TNSV THACO cup 2026), trực tiếp trên FPT Play và các nền tảng YouTube, Facebook của Báo Thanh Niên.",
    "source": "Thanh Niên",
    "category": "Tổng hợp",
    "published": "2026-03-16T17:00:00+07:00",
    "fetched": "2026-03-17T01:49:09.872546+07:00"
  },
  {
    "id": "a50454e4bb7ef38dea6441c1e93d4b10",
    "title": "Chuyến hộ tống tàu dầu từng khiến hải quân Mỹ 'mất mặt' trên Vịnh Ba Tư",
    "link": "https://vnexpress.net/chuyen-ho-tong-tau-dau-tung-khien-hai-quan-my-mat-mat-tren-vinh-ba-tu-5049759.html",
    "summary": "Mỹ từng mở chiến dịch hộ tống tàu dầu qua Eo biển Hormuz năm 1987, nhưng sự cố siêu tàu Bridgeton trúng thủy lôi đã giáng đòn vào hình ảnh hải quân nước này.",
    "source": "VnExpress - Thế Giới",
    "category": "Thế giới",
    "published": "2026-03-16T17:00:00+07:00",
    "fetched": "2026-03-17T01:49:12.148080+07:00"
  },
  {
    "id": "d78d6098174dc93d3836eca212642b85",
    "title": "Phạt 2 tỷ đồng nếu để xảy ra sự cố hạt nhân",
    "link": "https://vnexpress.net/phat-2-ty-dong-neu-de-xay-ra-su-co-hat-nhan-5051035.html",
    "summary": "Chính phủ quy định mức phạt hành chính cao nhất 2 tỷ đồng đối với hành vi không thực hiện các biện pháp ngăn ngừa để xảy ra sự cố tại nhà máy điện hạt nhân.",
    "source": "VnExpress - Công Nghệ",
    "category": "Công nghệ",
    "published": "2026-03-16T17:00:00+07:00",
    "fetched": "2026-03-17T01:49:16.359291+07:00"
  },
  {
    "id": "a97fe667c58c4011892ac4ee2d913a45",
    "title": "Chelsea bị cấm chuyển nhượng vì sai phạm thời Abramovich",
    "link": "https://vnexpress.net/chelsea-bi-cam-chuyen-nhuong-vi-sai-pham-thoi-abramovich-5051221.html",
    "summary": "Ngày 16/3, Ngoại hạng Anh phạt CLB Chelsea 14,3 triệu USD, kèm lệnh cấm chuyển nhượng đội một dưới hình thức án treo và cấm chuyển nhượng cấp học viện có hiệu lực ngay lập tức trong vòng 9 tháng.",
    "source": "VnExpress - Thể Thao",
    "category": "Thể thao",
    "published": "2026-03-16T17:00:00+07:00",
    "fetched": "2026-03-17T01:49:17.347695+07:00"
  },
  {
    "id": "1890af0ca78d64f3e7fc393f05894c90",
    "title": "Hàng nghìn áo ngực được ném xuống trận khúc côn cầu ở Mỹ",
    "link": "https://vnexpress.net/hang-nghin-ao-nguc-duoc-nem-xuong-tran-khuc-con-cau-o-my-5051195.html",
    "summary": "Trận khúc côn cầu nữ giữa Seattle Torrent và Boston Fleet phải tạm dừng khi hàng nghìn áo ngực thể thao được khán giả ném xuống sân băng, trong một hoạt động từ thiện hỗ trợ các bé gái chơi thể thao.",
    "source": "VnExpress - Thể Thao",
    "category": "Thể thao",
    "published": "2026-03-16T17:00:00+07:00",
    "fetched": "2026-03-17T01:49:17.347968+07:00"
  },
  {
    "id": "46afe984d4bcb59d6e797da01d48bb49",
    "title": "'Nữ hoàng tuyết' quyết không giải nghệ dù suýt mất chân",
    "link": "https://vnexpress.net/nu-hoang-tuyet-quyet-khong-giai-nghe-du-suyt-mat-chan-5051191.html",
    "summary": "VĐV trượt tuyết Lindsey Vonn khẳng định sẽ tự quyết định tương lai sự nghiệp, bất chấp lời kêu gọi giải nghệ sau tai nạn nghiêm trọng tại Olympic mùa Đông.",
    "source": "VnExpress - Thể Thao",
    "category": "Thể thao",
    "published": "2026-03-16T17:00:00+07:00",
    "fetched": "2026-03-17T01:49:17.348176+07:00"
  },
  {
    "id": "835e6ff7e824654c001666409a6c7ce4",
    "title": "Bayern mất cả 4 thủ môn ở Champions League",
    "link": "https://vnexpress.net/bayern-mat-ca-4-thu-mon-o-champions-league-5051187.html",
    "summary": "Bayern Munich đối mặt tình huống hy hữu khi cả bốn thủ môn trong đội một đều chấn thương, trước trận lượt về vòng 1/8 Champions League gặp Atalanta.",
    "source": "VnExpress - Thể Thao",
    "category": "Thể thao",
    "published": "2026-03-16T17:00:00+07:00",
    "fetched": "2026-03-17T01:49:17.348345+07:00"
  },
  {
    "id": "eb54f4c4371d587d31604437dffbc142",
    "title": "Sao bóng bầu dục Mỹ lo ồn ào đời tư ảnh hưởng giấc mơ Super Bowl",
    "link": "https://vnexpress.net/sao-bong-bau-duc-my-lo-on-ao-doi-tu-anh-huong-giac-mo-super-bowl-5050934.html",
    "summary": "Ngôi sao của Dallas Cowboys, Dak Prescott lo ngại những ồn ào sau khi chia tay hôn thê Sarah Jane Ramos có thể ảnh hưởng tới phong độ và tham vọng chinh phục danh hiệu Super Bowl.",
    "source": "VnExpress - Thể Thao",
    "category": "Thể thao",
    "published": "2026-03-16T17:00:00+07:00",
    "fetched": "2026-03-17T01:49:17.348504+07:00"
  },
  {
    "id": "328f029dd8512d4d33cb02613d56e2ac",
    "title": "Runner Mỹ xăm logo thông báo gia nhập giải cho phép dùng doping",
    "link": "https://vnexpress.net/runner-my-xam-logo-thong-bao-gia-nhap-giai-cho-phep-dung-doping-5050514.html",
    "summary": "VĐV nước rút Taylor Anderson thông báo gia nhập Enhanced Games, nơi cho phép sử dụng chất tăng cường thành tích, bằng việc xăm logo của giải lên cơ thể.",
    "source": "VnExpress - Thể Thao",
    "category": "Thể thao",
    "published": "2026-03-16T17:00:00+07:00",
    "fetched": "2026-03-17T01:49:17.348660+07:00"
  },
  {
    "id": "086c352b8aadeb0331a5ebc19943a2fb",
    "title": "Quảng Trị: Khởi tố một chủ cơ sở kinh doanh giò chả dương tính hàn the",
    "link": "https://thanhnien.vn/quang-tri-khoi-to-mot-chu-co-so-kinh-doanh-gio-cha-duong-tinh-han-the-185260316201525227.htm",
    "summary": "Công an tỉnh Quảng Trị vừa có quyết định khởi tố bị can một chủ cơ sở kinh doanh giò chả sau khi qua kiểm tra, phát hiện các sản phẩm của cơ sở này dương tính với hàn the.",
    "source": "Thanh Niên",
    "category": "Tổng hợp",
    "published": "2026-03-16T16:17:00+07:00",
    "fetched": "2026-03-17T01:49:09.872696+07:00"
  },
  {
    "id": "99dd80931e69ef5aa7fabb06654d9f16",
    "title": "'Vũ trụ say hi' bùng nổ đêm khai mạc Năm Du lịch quốc gia 2026",
    "link": "https://thanhnien.vn/vu-tru-say-hi-bung-no-dem-khai-mac-nam-du-lich-quoc-gia-2026-18526031618561982.htm",
    "summary": "Mega concert quy tụ dàn sao 'Vũ trụ say hi' hứa hẹn sẽ khuấy động đêm khai mạc Năm Du lịch quốc gia - Gia Lai 2026 tại quảng trường Nguyễn Tất Thành, phường Quy Nhơn, Gia Lai.",
    "source": "Thanh Niên",
    "category": "Tổng hợp",
    "published": "2026-03-16T15:45:00+07:00",
    "fetched": "2026-03-17T01:49:09.872843+07:00"
  },
  {
    "id": "3a322c858e7afeb115a7c3f8b082f7c0",
    "title": "Ba tàu dầu Pakistan băng qua Eo biển Hormuz an toàn",
    "link": "https://vnexpress.net/ba-tau-dau-pakistan-bang-qua-eo-bien-hormuz-an-toan-5051211.html",
    "summary": "Ba tàu dầu Pakistan đã vượt qua Eo biển Hormuz trong 10 ngày gần đây, cho thấy Iran có thể đang mở cửa tuyến hàng hải này với phương tiện một số nước.",
    "source": "VnExpress - Thế Giới",
    "category": "Thế giới",
    "published": "2026-03-16T15:31:05+07:00",
    "fetched": "2026-03-17T01:49:12.148266+07:00"
  },
  {
    "id": "fee3cd79e91250fc9141149cc2340b49",
    "title": "'Gia công phần mềm không thể giúp Việt Nam thành cường quốc công nghệ'",
    "link": "https://vnexpress.net/gia-cong-phan-mem-khong-the-giup-viet-nam-thanh-cuong-quoc-cong-nghe-5051190.html",
    "summary": "Thứ trưởng Khoa học và Công nghệ Bùi Hoàng Phương cho rằng gia công phần mềm đã giúp Việt Nam tạo bước đà quan trọng, nhưng không thể là cường quốc công nghệ.",
    "source": "VnExpress - Công Nghệ",
    "category": "Công nghệ",
    "published": "2026-03-16T15:14:45+07:00",
    "fetched": "2026-03-17T01:49:16.359466+07:00"
  },
  {
    "id": "d19f7219e721dfa23282734d9244ebf8",
    "title": "Phim kinh dị 18+ dẫn đầu phòng vé, 'Tài' của Mỹ Tâm giờ ra sao?",
    "link": "https://thanhnien.vn/phim-kinh-di-18-dan-dau-phong-ve-tai-cua-my-tam-gio-ra-sao-185260316212004108.htm",
    "summary": "Theo số liệu của Box Office Vietnam, phim kinh dị 'Quỷ nhập tràng 2' đang dẫn đầu phòng vé, thu hơn 77 tỉ đồng sau vài ngày ra rạp. Trong khi đó, 'Tài' của Mỹ Tâm sắp chạm mốc doanh thu trăm tỉ.",
    "source": "Thanh Niên",
    "category": "Tổng hợp",
    "published": "2026-03-16T15:08:00+07:00",
    "fetched": "2026-03-17T01:49:09.872992+07:00"
  },
  {
    "id": "b86750969bcba4516ef00541590f6501",
    "title": "Mỹ mở rộng cảnh báo đi lại vì mối đe dọa từ Iran",
    "link": "https://thanhnien.vn/my-mo-rong-canh-bao-di-lai-vi-moi-de-doa-tu-iran-185260316195211169.htm",
    "summary": "Bộ Ngoại giao Mỹ đã cập nhật cảnh báo đi lại cho công dân Mỹ, theo đó khuyến cáo người dân cân nhắc lại kế hoạch đến Trung Đông trong bối cảnh xung đột tại khu vực vẫn tiếp diễn.",
    "source": "Thanh Niên",
    "category": "Tổng hợp",
    "published": "2026-03-16T14:56:00+07:00",
    "fetched": "2026-03-17T01:49:09.873155+07:00"
  },
  {
    "id": "d88c5ba31b9a4bc1be36d70376170d10",
    "title": "VinFast thu hơn 90.000 tỷ đồng năm 2025",
    "link": "https://vnexpress.net/vinfast-thu-hon-90-000-ty-dong-nam-2025-5051209.html",
    "summary": "VinFast ghi nhận doanh thu 90.427 tỷ đồng trong năm 2025, tăng 139% so với thực hiện năm trước đó và cao nhất từ trước đến nay.",
    "source": "VnExpress - Kinh Doanh",
    "category": "Kinh doanh",
    "published": "2026-03-16T14:55:36+07:00",
    "fetched": "2026-03-17T01:49:13.653065+07:00"
  },
  {
    "id": "ea3ac2bf8e161120318752d900852efb",
    "title": "Malaysia: Ba người bị điện giật chết vì trộm dây cáp điện",
    "link": "https://thanhnien.vn/malaysia-ba-nguoi-bi-dien-giat-chet-vi-trom-day-cap-dien-185260316193300521.htm",
    "summary": "Trang Malay Mail hôm 16.3 đưa tin 3 người đàn ông đã tử vong trong lúc lấy trộm dây cáp điện ở một vùng đất trống tại khu dân cư Taman Rapat Perdana thuộc thành phố Ipoh, tây bắc Malaysia.",
    "source": "Thanh Niên",
    "category": "Tổng hợp",
    "published": "2026-03-16T14:55:00+07:00",
    "fetched": "2026-03-17T01:49:09.873305+07:00"
  },
  {
    "id": "0f7a773f638727eff9ad63f3e7ee1d8b",
    "title": "Trung vệ Đà Nẵng thần tượng CR7: ‘Đời sinh viên không có lần thứ 2 như thế này’",
    "link": "https://thanhnien.vn/trung-ve-da-nang-than-tuong-cr7-doi-sinh-vien-khong-co-lan-thu-2-nhu-the-nay-185260316213254546.htm",
    "summary": "Trở lại giải đấu với nỗi đau từ trận chung kết năm ngoái, chàng trai mang áo số 12 Nguyễn Lê Tuấn Đạt của Trường ĐH TDTT Đà Nẵng đã có những chia sẻ đầy xúc động về thần tượng CR7 và \"điểm tựa\" gia đình – nơi đã giúp em vượt qua ý định bỏ cuộc để tiếp tục cháy hết mình trong mùa giải TNSV 2026.",
    "source": "Thanh Niên",
    "category": "Tổng hợp",
    "published": "2026-03-16T14:49:00+07:00",
    "fetched": "2026-03-17T01:49:09.873452+07:00"
  },
  {
    "id": "48951919226bf0b0eb0df5ffb2177edc",
    "title": "Nóng: FIFA gỡ toàn bộ án cấm chuyển nhượng sát giờ G, Thanh Hóa bổ sung ngay 7 cầu thủ giỏi",
    "link": "https://thanhnien.vn/nong-fifa-go-toan-bo-an-cam-chuyen-nhuong-sat-gio-g-thanh-hoa-bo-sung-ngay-7-cau-thu-gioi-185260316214446389.htm",
    "summary": "CLB Thanh Hóa đã chính thức được phép hoạt động trở lại trên thị trường chuyển nhượng sau khi Liên đoàn Bóng đá thế giới (FIFA) gỡ bỏ các án cấm đăng ký cầu thủ mới.",
    "source": "Thanh Niên",
    "category": "Tổng hợp",
    "published": "2026-03-16T14:48:00+07:00",
    "fetched": "2026-03-17T01:49:09.873596+07:00"
  },
  {
    "id": "d90495125b070d8d7242e84bd3db53f0",
    "title": "Khi nào khôi phục chạy tàu qua khu gian Hải Vân - Hải Vân Nam?",
    "link": "https://thanhnien.vn/khi-nao-khoi-phuc-chay-tau-qua-khu-gian-hai-van-hai-van-nam-185260316202723698.htm",
    "summary": "Sau sự cố đá tảng lăn làm gãy đường ray, gây trật bánh tàu hàng và gián đoạn tuyến đường sắt Bắc - Nam qua đèo Hải Vân, ngành đường sắt dự kiến khôi phục chạy tàu qua khu vực này từ rạng sáng 17.3.",
    "source": "Thanh Niên",
    "category": "Tổng hợp",
    "published": "2026-03-16T14:46:00+07:00",
    "fetched": "2026-03-17T01:49:09.873740+07:00"
  },
  {
    "id": "095e6fa936624310125012e2971a87c8",
    "title": "Quảng Trị: Cháu bé sơ sinh bị bỏ rơi dưới hầm chui cao tốc",
    "link": "https://thanhnien.vn/quang-tri-chau-be-so-sinh-bi-bo-roi-duoi-ham-chui-cao-toc-185260316202611782.htm",
    "summary": "Chính quyền địa phương xã Nam Gianh (Quảng Trị) đã thông báo để tìm lại cha mẹ ruột của một cháu bé sơ sinh được người dân phát hiện dưới hầm chui cao tốc.",
    "source": "Thanh Niên",
    "category": "Tổng hợp",
    "published": "2026-03-16T14:42:00+07:00",
    "fetched": "2026-03-17T01:49:09.873898+07:00"
  },
  {
    "id": "e1576f1dc3c326bdef30866079490b80",
    "title": "Apple ra AirPods Max 2 chống ồn tốt hơn, giá 15 triệu đồng",
    "link": "https://vnexpress.net/apple-ra-airpods-max-2-chong-on-tot-hon-gia-15-trieu-dong-5051204.html",
    "summary": "Apple giới thiệu tai nghe mới AirPods Max 2, nâng cấp chip H2 cho khả năng chống ồn tốt hơn, âm thanh trong hơn và giá 15 triệu đồng.",
    "source": "VnExpress - Công Nghệ",
    "category": "Công nghệ",
    "published": "2026-03-16T14:28:51+07:00",
    "fetched": "2026-03-17T01:49:16.359627+07:00"
  },
  {
    "id": "2644668adec36ca0ba3911359d560fae",
    "title": "Thủ tướng Israel tiếp tục đăng video chứng minh mình còn sống",
    "link": "https://vnexpress.net/thu-tuong-israel-tiep-tuc-dang-video-chung-minh-minh-con-song-5051201.html",
    "summary": "Thủ tướng Israel Netanyahu đăng video thứ hai trong vòng chưa đầy 24 giờ nhằm bác bỏ những tin đồn rằng ông đã chết hoặc bị thương vì tên lửa Iran.",
    "source": "VnExpress - Thế Giới",
    "category": "Thế giới",
    "published": "2026-03-16T14:25:09+07:00",
    "fetched": "2026-03-17T01:49:12.148435+07:00"
  },
  {
    "id": "b9239f6036fbffa58bf9c81d7bcc5702",
    "title": "LPBank và Novaland ký hợp tác cho khách hàng vay mua bất động sản",
    "link": "https://thanhnien.vn/lpbank-va-novaland-ky-hop-tac-cho-khach-hang-vay-mua-bat-dong-san-185260316205540419.htm",
    "summary": "Ngày 16.3, Ngân hàng TMCP Lộc Phát Việt Nam (LPBank) và Công ty cổ phần Tập đoàn đầu tư địa ốc No Va (Novaland) đã ký kết thỏa thuận hợp tác toàn diện, thiết lập quan hệ đối tác chiến lược giữa hai doanh nghiệp lớn trong lĩnh vực tài chính - ngân hàng và bất động sản.",
    "source": "Thanh Niên",
    "category": "Tổng hợp",
    "published": "2026-03-16T14:21:00+07:00",
    "fetched": "2026-03-17T01:49:09.874046+07:00"
  },
  {
    "id": "7498abd7122647696d60410c74cea06c",
    "title": "Người Tehran sợ hãi, tuyệt vọng dưới mưa bom",
    "link": "https://vnexpress.net/nguoi-tehran-so-hai-tuyet-vong-duoi-mua-bom-5051192.html",
    "summary": "Một số người dân Tehran cho biết họ đang sống trong cả sợ hãi lẫn tuyệt vọng khi liên tục phải hứng chịu những cuộc không kích dữ dội từ Mỹ - Israel.",
    "source": "VnExpress - Thế Giới",
    "category": "Thế giới",
    "published": "2026-03-16T13:47:02+07:00",
    "fetched": "2026-03-17T01:49:12.148631+07:00"
  },
  {
    "id": "37c912a1297472322ef91ebf1feade58",
    "title": "Thủ tướng: Xem xét bố trí ngân sách để bình ổn giá xăng dầu",
    "link": "https://vnexpress.net/thu-tuong-xem-xet-bo-tri-ngan-sach-de-binh-on-gia-xang-dau-5051196.html",
    "summary": "Thủ tướng nói Việt Nam dứt khoát không để thiếu xăng dầu và nếu xung đột Trung Đông kéo dài, có thể xem xét bố trí ngân sách hỗ trợ bình ổn giá.",
    "source": "VnExpress - Kinh Doanh",
    "category": "Kinh doanh",
    "published": "2026-03-16T13:34:17+07:00",
    "fetched": "2026-03-17T01:49:13.653268+07:00"
  },
  {
    "id": "669f2805714f597803c82763372e1cb8",
    "title": "Tranh cãi về bức ảnh cá mập Greenland 392 tuổi",
    "link": "https://vnexpress.net/tranh-cai-ve-buc-anh-ca-map-greenland-392-tuoi-5051182.html",
    "summary": "Ảnh chụp cá mập Greenland với chú thích 392 tuổi gây chú ý trên mạng xã hội, nhưng các nhà nghiên cứu suy đoán nó hơn 150 tuổi.",
    "source": "VnExpress - Công Nghệ",
    "category": "Công nghệ",
    "published": "2026-03-16T13:12:10+07:00",
    "fetched": "2026-03-17T01:49:16.359946+07:00"
  },
  {
    "id": "b17aee4fbb1232fb43e42daad271ec93",
    "title": "Iran mỉa mai ông Trump vì kêu gọi đồng minh giúp mở lại Eo biển Hormuz",
    "link": "https://vnexpress.net/iran-mia-mai-ong-trump-vi-keu-goi-dong-minh-giup-mo-lai-eo-bien-hormuz-5051178.html",
    "summary": "Ngoại trưởng Iran mỉa mai Tổng thống Mỹ vì vừa kêu gọi các đồng minh hỗ trợ mở lại Eo biển Hormuz, vừa yêu cầu Tehran đầu hàng.",
    "source": "VnExpress - Thế Giới",
    "category": "Thế giới",
    "published": "2026-03-16T12:30:22+07:00",
    "fetched": "2026-03-17T01:49:12.148797+07:00"
  },
  {
    "id": "f93c56c68708b3ac08df3830c305c59e",
    "title": "Tổng Bí thư: Việt - Trung sẽ tiếp tục nâng tầm gắn kết chiến lược",
    "link": "https://vnexpress.net/tong-bi-thu-viet-trung-se-tiep-tuc-nang-tam-gan-ket-chien-luoc-5051185.html",
    "summary": "Tổng Bí thư Tô Lâm tiếp lãnh đạo các Bộ Ngoại giao, Quốc phòng, Công an Trung Quốc, khẳng định phát triển quan hệ song phương là ưu tiên hàng đầu, mong muốn tiếp tục nâng tầm gắn kết chiến lược giữa hai nước.",
    "source": "VnExpress - Thế Giới",
    "category": "Thế giới",
    "published": "2026-03-16T12:12:11+07:00",
    "fetched": "2026-03-17T01:49:12.148954+07:00"
  },
  {
    "id": "1e43514655e698bbd3a825fb3f1a06a8",
    "title": "SCB chuẩn bị đấu giá nhà đất, quần áo liên quan bà Trương Mỹ Lan",
    "link": "https://vnexpress.net/scb-chuan-bi-dau-gia-nha-dat-quan-ao-lien-quan-ba-truong-my-lan-5051184.html",
    "summary": "SCB đang tìm đơn vị tư vấn đấu thầu để xử lý 12 loại tài sản liên quan bà Trương Mỹ Lan như bất động sản, ôtô, quần áo, túi xách…",
    "source": "VnExpress - Kinh Doanh",
    "category": "Kinh doanh",
    "published": "2026-03-16T12:11:22+07:00",
    "fetched": "2026-03-17T01:49:13.653432+07:00"
  },
  {
    "id": "c8b9baef2546fb1f4c80bb176f48686e",
    "title": "Trung Quốc tự tin vào nguồn cung năng lượng",
    "link": "https://vnexpress.net/trung-quoc-tu-tin-vao-nguon-cung-nang-luong-5051108.html",
    "summary": "Bắc Kinh khẳng định nguồn cung năng lượng của nước này đủ đối phó với biến động giá dầu, khí toàn cầu 2 tuần qua.",
    "source": "VnExpress - Kinh Doanh",
    "category": "Kinh doanh",
    "published": "2026-03-16T12:02:00+07:00",
    "fetched": "2026-03-17T01:49:13.653590+07:00"
  },
  {
    "id": "ce40a3a054699c386a1563d18617321a",
    "title": "Chiến dịch 'từ phủ đầu đến sửa sai' của Mỹ nhắm vào Iran",
    "link": "https://vnexpress.net/chien-dich-tu-phu-dau-den-sua-sai-cua-my-nham-vao-iran-5050797.html",
    "summary": "Chiến dịch phủ đầu của ông Trump vào Iran dường như chệch hướng ngay từ đầu, đẩy Mỹ vào cuộc chiến không lối thoát và buộc Nhà Trắng tìm cách sửa sai.",
    "source": "VnExpress - Thế Giới",
    "category": "Thế giới",
    "published": "2026-03-16T12:00:00+07:00",
    "fetched": "2026-03-17T01:49:12.149107+07:00"
  },
  {
    "id": "3a8362c0c8c8c0a6ba930a66eba95f51",
    "title": "Lũ lụt biến đường phố thành sông ở Hawaii",
    "link": "https://vnexpress.net/lu-lut-bien-duong-pho-thanh-song-o-hawaii-5051144.html",
    "summary": "Những trận mưa \"lớn chưa từng thấy trong 20 năm\" trút xuống Hawaii gây lũ quét nhấn chìm đường phố, phá hủy hạ tầng, khiến hàng chục nghìn hộ mất điện.",
    "source": "VnExpress - Thế Giới",
    "category": "Thế giới",
    "published": "2026-03-16T11:51:46+07:00",
    "fetched": "2026-03-17T01:49:12.149299+07:00"
  },
  {
    "id": "b9efba9156365cfb9ea9af88f2066496",
    "title": "Nhiều nước từ chối cử chiến hạm hộ tống tàu dầu đi qua Eo biển Hormuz",
    "link": "https://vnexpress.net/nhieu-nuoc-tu-choi-cu-chien-ham-ho-tong-tau-dau-di-qua-eo-bien-hormuz-5051105.html",
    "summary": "Lãnh đạo nhiều nước không đồng ý với lời kêu gọi của Tổng thống Mỹ về việc cử chiến hạm hộ tống tàu qua Eo biển Hormuz.",
    "source": "VnExpress - Thế Giới",
    "category": "Thế giới",
    "published": "2026-03-16T11:32:49+07:00",
    "fetched": "2026-03-17T01:49:12.149454+07:00"
  },
  {
    "id": "41e93492803c3bf60981f734e09076fb",
    "title": "Sun Group lập sàn giao dịch tiền số",
    "link": "https://vnexpress.net/sun-group-lap-san-giao-dich-tien-so-5051174.html",
    "summary": "Sun Group góp 64% trong 1.000 tỷ đồng vốn điều lệ ban đầu của Công ty cổ phần Tài sản số Việt Nam với chức năng lập sàn giao dịch.",
    "source": "VnExpress - Kinh Doanh",
    "category": "Kinh doanh",
    "published": "2026-03-16T11:02:51+07:00",
    "fetched": "2026-03-17T01:49:13.653746+07:00"
  },
  {
    "id": "22c709d898a078f59f6a5b2c2a326983",
    "title": "Liên danh Việt - Hà Lan đầu tư bến cảng container Liên Chiểu gần 1,8 tỷ USD",
    "link": "https://vnexpress.net/lien-danh-viet-ha-lan-dau-tu-ben-cang-container-lien-chieu-gan-1-8-ty-usd-5051132.html",
    "summary": "Liên danh Hateco và APM Terminals (Hà Lan) được chọn đầu tư bến cảng container Liên Chiểu tại Đà Nẵng, tổng vốn khoảng 1,76 tỷ USD.",
    "source": "VnExpress - Kinh Doanh",
    "category": "Kinh doanh",
    "published": "2026-03-16T10:50:22+07:00",
    "fetched": "2026-03-17T01:49:13.653903+07:00"
  },
  {
    "id": "14341937537cdc8862919b25858cbde9",
    "title": "Israel tuyên bố phá hủy chuyên cơ của cố lãnh tụ tối cao Iran",
    "link": "https://vnexpress.net/israel-tuyen-bo-pha-huy-chuyen-co-cua-co-lanh-tu-toi-cao-iran-5051157.html",
    "summary": "Không quân Israel nói đã tấn công và phá hủy máy bay của cố lãnh tụ tối cao Iran Ali Khamenei tại sân bay Mehrabad ở Tehran trong đêm.",
    "source": "VnExpress - Thế Giới",
    "category": "Thế giới",
    "published": "2026-03-16T10:35:59+07:00",
    "fetched": "2026-03-17T01:49:12.149607+07:00"
  },
  {
    "id": "40dd7f3bd688ce04293d1e6162c555a7",
    "title": "Kuwait có thể đã mất loạt tiêm kích hơn 100 triệu USD do xung đột",
    "link": "https://vnexpress.net/kuwait-co-the-da-mat-loat-tiem-kich-hon-100-trieu-usd-do-xung-dot-5051072.html",
    "summary": "Ảnh vệ tinh cho thấy đòn tập kích của Iran làm hư hại ít nhất một tiêm kích Typhoon Kuwait và kho chứa UAV Mỹ ở căn cứ Ali Al-Salem.",
    "source": "VnExpress - Thế Giới",
    "category": "Thế giới",
    "published": "2026-03-16T10:13:35+07:00",
    "fetched": "2026-03-17T01:49:12.149758+07:00"
  },
  {
    "id": "5c00d2a38b62b1c47bf31a1bfe7c37cd",
    "title": "Carragher: 'Tottenham cứ như ông lớn vì Liverpool quá dở'",
    "link": "https://vnexpress.net/carragher-tottenham-cu-nhu-ong-lon-vi-liverpool-qua-do-5051129.html",
    "summary": "Cựu danh thủ Jamie Carragher miêu tả Liverpool tệ đến mức đối thủ đang vật lộn trụ hạng lại trông như một đội bóng lớn, sau trận hòa Tottenham 1-1 ở vòng 30 Ngoại hạng Anh.",
    "source": "VnExpress - Thể Thao",
    "category": "Thể thao",
    "published": "2026-03-16T10:00:00+07:00",
    "fetched": "2026-03-17T01:49:17.348815+07:00"
  },
  {
    "id": "26ad90cf4f613b54a7917d5ab39f6cc2",
    "title": "30 tỷ hình ảnh thu thập từ Pokémon Go được dùng để huấn luyện robot",
    "link": "https://vnexpress.net/30-ty-hinh-anh-thu-thap-tu-pokemon-go-duoc-dung-de-huan-luyen-robot-5051054.html",
    "summary": "Nhà phát triển Pokemon Go cho biết dữ liệu hơn 30 tỷ hình ảnh do người chơi chụp trên khắp thế giới sẽ được sử dụng để giúp robot giao hàng điều hướng.",
    "source": "VnExpress - Công Nghệ",
    "category": "Công nghệ",
    "published": "2026-03-16T09:59:41+07:00",
    "fetched": "2026-03-17T01:49:16.360097+07:00"
  },
  {
    "id": "f61d7b2765ba6fd0afa11b80836bdff8",
    "title": "UAV đánh trúng bể dầu, sân bay Dubai đóng cửa",
    "link": "https://vnexpress.net/uav-danh-trung-be-dau-san-bay-dubai-dong-cua-5051131.html",
    "summary": "UAV đánh trúng bể chứa dầu tại sân bay quốc tế Dubai, dẫn đến đám cháy lớn và buộc cơ sở này đóng cửa nhiều giờ.",
    "source": "VnExpress - Thế Giới",
    "category": "Thế giới",
    "published": "2026-03-16T09:54:09+07:00",
    "fetched": "2026-03-17T01:49:12.149915+07:00"
  },
  {
    "id": "dfc485ffb7e9d45e6b0ea8047f5ba0a0",
    "title": "Vinaconex muốn bán 18% vốn công ty con",
    "link": "https://vnexpress.net/vinaconex-muon-ban-18-von-cong-ty-con-5051098.html",
    "summary": "Vinaconex đăng ký bán 18% vốn của Viwaseen, công ty trong hệ sinh thái, sau khi giá cổ phiếu doanh nghiệp này tăng gần gấp 3 lần trong 7 phiên.",
    "source": "VnExpress - Kinh Doanh",
    "category": "Kinh doanh",
    "published": "2026-03-16T09:39:02+07:00",
    "fetched": "2026-03-17T01:49:13.654077+07:00"
  },
  {
    "id": "10471e0cf0d1eeaaf6a4fca2e41e88e4",
    "title": "Những phụ nữ Nhật đòi quyền triệt sản",
    "link": "https://vnexpress.net/nhung-phu-nu-nhat-doi-quyen-triet-san-5050123.html",
    "summary": "Khi Kazane Kajiya quyết định triệt sản vào năm 27 tuổi ở Mỹ, cô xem đó là hành động phản kháng xã hội phụ hệ Nhật Bản.",
    "source": "VnExpress - Thế Giới",
    "category": "Thế giới",
    "published": "2026-03-16T09:27:55+07:00",
    "fetched": "2026-03-17T01:49:12.150069+07:00"
  },
  {
    "id": "b20d64137b5ab44d7fd18c813d61b6a0",
    "title": "Diomande - ngọc thô tuổi teen gây sốt toàn châu Âu",
    "link": "https://vnexpress.net/diomande-ngoc-tho-tuoi-teen-gay-sot-toan-chau-au-5051081.html",
    "summary": "Cầu thủ chạy cánh 19 tuổi Yan Diomande đang là mục tiêu săn đón toàn châu Âu, với phong cách như Vinicius Junior và thông số tiệm cận Lamine Yamal.",
    "source": "VnExpress - Thể Thao",
    "category": "Thể thao",
    "published": "2026-03-16T09:23:03+07:00",
    "fetched": "2026-03-17T01:49:17.348973+07:00"
  },
  {
    "id": "65cef763a88b6d62153f425799658b0b",
    "title": "Công ty bầu Đức dự kiến đầu tư 20.000 ha cà phê",
    "link": "https://vnexpress.net/cong-ty-bau-duc-du-kien-dau-tu-20-000-ha-ca-phe-5051049.html",
    "summary": "Hoàng Anh Gia Lai dự kiến phát triển 20.000 ha cà phê đến năm 2028, kỳ vọng doanh thu hơn 700 triệu USD mỗi năm và thành doanh nghiệp quản lý vùng trồng cà phê lớn nhất thế giới.",
    "source": "VnExpress - Kinh Doanh",
    "category": "Kinh doanh",
    "published": "2026-03-16T09:19:56+07:00",
    "fetched": "2026-03-17T01:49:13.654251+07:00"
  },
  {
    "id": "1675efb6dd4aaa3f75ef63fd1774fce1",
    "title": "Neville: 'Casemiro rời Man Utd cuối mùa là đúng'",
    "link": "https://vnexpress.net/neville-casemiro-roi-man-utd-cuoi-mua-la-dung-5051124.html",
    "summary": "Cựu danh thủ Gary Neville cho rằng Man Utd vẫn đúng khi quyết định để Casemiro ra đi vào cuối mùa, dù đây đang là quân bài quan trọng bậc nhất của HLV Michael Carrick.",
    "source": "VnExpress - Thể Thao",
    "category": "Thể thao",
    "published": "2026-03-16T09:14:05+07:00",
    "fetched": "2026-03-17T01:49:17.349243+07:00"
  },
  {
    "id": "e70d16d138324eb92f8e0a0253139d2c",
    "title": "VN-Index giảm ba phiên liên tiếp",
    "link": "https://vnexpress.net/vn-index-giam-ba-phien-lien-tiep-5051087.html",
    "summary": "VN-Index đảo chiều từ tăng thành giảm bởi áp lực xả hàng cổ phiếu dầu khí, qua đó nối dài mạch điều chỉnh ba phiên liên tiếp và đóng cửa dưới 1.700 điểm.",
    "source": "VnExpress - Kinh Doanh",
    "category": "Kinh doanh",
    "published": "2026-03-16T08:34:04+07:00",
    "fetched": "2026-03-17T01:49:13.654407+07:00"
  },
  {
    "id": "85b9562c087f2a5538c2daa5497f2dd7",
    "title": "Internet vệ tinh Starlink dự kiến có giá 2,2 triệu mỗi tháng tại Việt Nam",
    "link": "https://vnexpress.net/internet-ve-tinh-starlink-du-kien-co-gia-2-2-trieu-moi-thang-tai-viet-nam-5051073.html",
    "summary": "Dịch vụ Internet vệ tinh Starlink tại Việt Nam dự kiến có giá thiết bị 9,2 triệu và cước thuê bao hàng tháng 2,2 triệu đồng.",
    "source": "VnExpress - Công Nghệ",
    "category": "Công nghệ",
    "published": "2026-03-16T08:21:21+07:00",
    "fetched": "2026-03-17T01:49:16.359788+07:00"
  },
  {
    "id": "9de6283b64c8135c6c0e80d5d8aac54a",
    "title": "Việt Nam sản xuất và tiêu thụ xăng dầu thế nào?",
    "link": "https://vnexpress.net/viet-nam-san-xuat-va-tieu-thu-xang-dau-the-nao-5050737.html",
    "summary": "Dù dành phần lớn dầu thô khai thác cho các nhà máy lọc nội địa, Việt Nam vẫn phải nhập khẩu 30% lượng xăng dầu để đáp ứng nhu cầu tiêu thụ.",
    "source": "VnExpress - Kinh Doanh",
    "category": "Kinh doanh",
    "published": "2026-03-16T08:18:34+07:00",
    "fetched": "2026-03-17T01:49:13.654559+07:00"
  },
  {
    "id": "3892e7f24a8399c13370b1a9f3ea3968",
    "title": "Israel thừa nhận tiêm kích suýt bị Iran bắn rơi",
    "link": "https://vnexpress.net/israel-thua-nhan-tiem-kich-suyt-bi-iran-ban-roi-5051056.html",
    "summary": "Quân đội Israel cho biết một tiêm kích suýt trúng đạn trên bầu trời Iran, nhưng không nêu cụ thể tình huống dẫn đến sự việc.",
    "source": "VnExpress - Thế Giới",
    "category": "Thế giới",
    "published": "2026-03-16T08:12:22+07:00",
    "fetched": "2026-03-17T01:49:12.150243+07:00"
  },
  {
    "id": "5a80811d93c0da489bdefb025235c2dc",
    "title": "AFC: Tuyển Malaysia khó bị đình chỉ thi đấu như Timor Leste",
    "link": "https://vnexpress.net/afc-tuyen-malaysia-kho-bi-dinh-chi-thi-dau-nhu-timor-leste-5051058.html",
    "summary": "Theo Tổng thư ký LĐBĐ châu Á (AFC) Datuk Seri Windsor John, tuy cùng vấn đề gian lận nhập tịch, bối cảnh khác nhau có thể khiến cách xử lý Malaysia khác với Timor Leste cách đây ít năm.",
    "source": "VnExpress - Thể Thao",
    "category": "Thể thao",
    "published": "2026-03-16T07:57:11+07:00",
    "fetched": "2026-03-17T01:49:17.349502+07:00"
  },
  {
    "id": "c688ebc09f2ebf0a2b8b4e67744a5c2f",
    "title": "Ngư dân sông Nile đổi sang 'săn' rác nhựa bởi quá ít cá",
    "link": "https://vnexpress.net/ngu-dan-song-nile-doi-sang-san-rac-nhua-boi-qua-it-ca-5051000.html",
    "summary": "Lượng cá sụt giảm nghiêm trọng vì rác nhựa khiến hàng trăm ngư dân Ai Cập phải bỏ nghề truyền thống, chuyển sang thu gom phế liệu để mưu sinh.",
    "source": "VnExpress - Kinh Doanh",
    "category": "Kinh doanh",
    "published": "2026-03-16T07:31:55+07:00",
    "fetched": "2026-03-17T01:49:13.654711+07:00"
  },
  {
    "id": "3a77cca65e80515a737c47d152df1129",
    "title": "Những điểm mới của AirTag 2 giá 890.000 đồng",
    "link": "https://vnexpress.net/nhung-diem-moi-cua-airtag-2-gia-890-000-dong-5051038.html",
    "summary": "AirTag 2, được bán tại Việt Nam từ 11/3, giữ nguyên giá 890.000 đồng như thế hệ trước, nhưng loa lớn hơn, kết nối và tìm thiết bị ở xa hơn nhờ chip Ultra Wideband 2.",
    "source": "VnExpress - Công Nghệ",
    "category": "Công nghệ",
    "published": "2026-03-16T07:30:22+07:00",
    "fetched": "2026-03-17T01:49:16.360273+07:00"
  },
  {
    "id": "bf76c69d87325050502e5feb5a549f15",
    "title": "Keane phản đối Man Utd ký dài hạn với Carrick",
    "link": "https://vnexpress.net/keane-phan-doi-man-utd-ky-dai-han-voi-carrick-5050835.html",
    "summary": "Theo huyền thoại Roy Keane, Michael Carrick vẫn không phải lựa chọn phù hợp để dẫn dắt Man Utd lâu dài, trái ngược quan điểm ủng hộ tuyệt đối từ Wayne Rooney.",
    "source": "VnExpress - Thể Thao",
    "category": "Thể thao",
    "published": "2026-03-16T06:00:00+07:00",
    "fetched": "2026-03-17T01:49:17.349980+07:00"
  },
  {
    "id": "1ca49bf071eb624c7670f2d7563d3feb",
    "title": "'Iran nắm chìa khóa mở lại thị trường năng lượng toàn cầu'",
    "link": "https://vnexpress.net/iran-nam-chia-khoa-mo-lai-thi-truong-nang-luong-toan-cau-5050790.html",
    "summary": "Iran đang gửi đi thông điệp cho thấy họ, chứ không phải Mỹ, mới là bên quyết định thời điểm chấm dứt gián đoạn nguồn cung năng lượng toàn cầu, theo Reuters.",
    "source": "VnExpress - Kinh Doanh",
    "category": "Kinh doanh",
    "published": "2026-03-16T05:05:00+07:00",
    "fetched": "2026-03-17T01:49:13.654865+07:00"
  },
  {
    "id": "a19b4b6c3c1c73270e5ffb5c6c2b8d4f",
    "title": "'Làm theo trực giác khiến nhiều nhà đầu tư thua lỗ'",
    "link": "https://vnexpress.net/lam-theo-truc-giac-khien-nhieu-nha-dau-tu-thua-lo-5050834.html",
    "summary": "Theo chuyên gia, hành động theo trực giác xuất phát từ thiên kiến mặc định trong não bộ khiến nhiều nhà đầu tư đưa ra quyết định thua lỗ.",
    "source": "VnExpress - Kinh Doanh",
    "category": "Kinh doanh",
    "published": "2026-03-16T05:01:04+07:00",
    "fetched": "2026-03-17T01:49:13.655025+07:00"
  },
  {
    "id": "f6bece36204534620f15976b8585d963",
    "title": "8 điểm nhấn vòng 30 Ngoại hạng Anh",
    "link": "https://vnexpress.net/8-diem-nhan-vong-30-ngoai-hang-anh-5050851.html",
    "summary": "Khoảnh khắc sao trẻ Max Dowman bước ra ánh sáng, Bruno Fernandes phá kỷ lục của David Beckham hay Liverpool tiếp tục thủng lưới phút cuối nằm trong danh sách điểm nhấn tại Ngoại hạng Anh cuối tuần qua.",
    "source": "VnExpress - Thể Thao",
    "category": "Thể thao",
    "published": "2026-03-16T05:00:00+07:00",
    "fetched": "2026-03-17T01:49:17.349671+07:00"
  },
  {
    "id": "8a09f3d3c011ec683d123b82f7bcf7e1",
    "title": "Hai anh em tự chế robot xoay rubik",
    "link": "https://vnexpress.net/hai-anh-em-tu-che-robot-xoay-rubik-5050896.html",
    "summary": "The Revenger, robot tự chế của hai anh em Matthew và Thomas Pidden (Anh), lập kỷ lục thế giới về thời gian giải khối rubik 4x4x4 ngắn nhất.",
    "source": "VnExpress - Công Nghệ",
    "category": "Công nghệ",
    "published": "2026-03-16T03:25:32+07:00",
    "fetched": "2026-03-17T01:49:16.360428+07:00"
  },
  {
    "id": "a982963823743e631e220d93dc7de6e7",
    "title": "Sinner hạ Medvedev, vô địch Indian Wells",
    "link": "https://vnexpress.net/sinner-ha-medvedev-vo-dich-indian-wells-5050886.html",
    "summary": "Hạt giống số hai Jannik Sinner thắng 7-6(6), 7-6(4) trước Daniil Medvedev trong trận chung kết Indian Wells Masters, hôm 15/3.",
    "source": "VnExpress - Thể Thao",
    "category": "Thể thao",
    "published": "2026-03-16T03:01:21+07:00",
    "fetched": "2026-03-17T01:49:17.350183+07:00"
  },
  {
    "id": "51535290f56188b9b55760b984c9a800",
    "title": "Iran 'đập tan âm mưu của kẻ thù' vụ cầu thủ nữ rút đơn tị nạn",
    "link": "https://vnexpress.net/iran-dap-tan-am-muu-cua-ke-thu-vu-cau-thu-nu-rut-don-ti-nan-5050852.html",
    "summary": "Báo Iran Tasnim cho rằng việc 5 trong 7 thành viên tuyển bóng đá nữ nước này rút đơn tị nạn ở Australia là \"quyết định yêu nước\", \"thoát khỏi cái bẫy của Mỹ\".",
    "source": "VnExpress - Thể Thao",
    "category": "Thể thao",
    "published": "2026-03-16T02:59:34+07:00",
    "fetched": "2026-03-17T01:49:17.350374+07:00"
  },
  {
    "id": "a345ddd06f1a0f4ffe3904db09f4f4f8",
    "title": "Sony WF-1000XM6 nâng cấp chống ồn, âm thanh 32 bit",
    "link": "https://vnexpress.net/sony-wf-1000xm6-nang-cap-chong-on-am-thanh-32-bit-5050540.html",
    "summary": "WF-1000XM6, tai nghe TWS đầu bảng của Sony, có khả năng khử ổn tốt hơn 25% so với thế hệ trước, khả năng xử lý âm thanh 32 bit.",
    "source": "VnExpress - Công Nghệ",
    "category": "Công nghệ",
    "published": "2026-03-16T02:00:00+07:00",
    "fetched": "2026-03-17T01:49:16.360579+07:00"
  },
  {
    "id": "7c658798e9c7a938a9ea5d6688213081",
    "title": "Giá chip nhớ sẽ 'bóp nghẹt' phân khúc điện thoại giá rẻ",
    "link": "https://vnexpress.net/gia-chip-nho-se-bop-nghet-phan-khuc-dien-thoai-gia-re-5050696.html",
    "summary": "Chip nhớ liên tục tăng giá và chiếm tỷ trọng lớn trong cơ cấu giá thành smartphone, khiến nhiều nhà sản xuất điện thoại phải điều chỉnh giá bán.",
    "source": "VnExpress - Công Nghệ",
    "category": "Công nghệ",
    "published": "2026-03-16T00:00:00+07:00",
    "fetched": "2026-03-17T01:49:16.360737+07:00"
  },
  {
    "id": "b088dfd5b8b5a6232c99452c5933b96d",
    "title": "Cơn sốt OpenClaw 'đảo chiều' tại Trung Quốc",
    "link": "https://vnexpress.net/con-sot-openclaw-dao-chieu-tai-trung-quoc-5050537.html",
    "summary": "Từng xếp hàng cài đặt OpenClaw, nhiều người dùng Trung Quốc hiện chi tiền nhờ gỡ tác nhân AI này khỏi thiết bị vì lo ngại bảo mật.",
    "source": "VnExpress - Công Nghệ",
    "category": "Công nghệ",
    "published": "2026-03-15T22:00:00+07:00",
    "fetched": "2026-03-17T01:49:16.360889+07:00"
  },
  {
    "id": "b00ec84a9ded77e3a7c8ef865cb62cf6",
    "title": "VĐV Ethiopia suýt phá kỷ lục thế giới nữ ngay lần đầu chạy marathon",
    "link": "https://vnexpress.net/vdv-ethiopia-suyt-pha-ky-luc-the-gioi-nu-ngay-lan-dau-chay-marathon-5050757.html",
    "summary": "Fotyen Tesfay đạt thành tích nhanh thứ hai lịch sử marathon nữ ngay lần đầu chạy cự ly 42,195 km tại Barcelona Marathon 2026.",
    "source": "VnExpress - Thể Thao",
    "category": "Thể thao",
    "published": "2026-03-15T21:55:58+07:00",
    "fetched": "2026-03-17T01:49:17.349828+07:00"
  },
  {
    "id": "93ecc11a227b00e119f1de30a7ea96af",
    "title": "Vì sao Đài Loan hình thành các 'chaebol' tài chính từ bảo hiểm nhân thọ?",
    "link": "https://vnexpress.net/vi-sao-dai-loan-hinh-thanh-cac-chaebol-tai-chinh-tu-bao-hiem-nhan-tho-5046576.html",
    "summary": "Với trục lõi là bảo hiểm nhân thọ, Đài Loan hình thành nên những 'chaebol' tài chính có độ phủ rộng lớn khắp nền kinh tế.",
    "source": "VnExpress - Kinh Doanh",
    "category": "Kinh doanh",
    "published": "2026-03-15T21:23:21+07:00",
    "fetched": "2026-03-17T01:49:13.655203+07:00"
  },
  {
    "id": "077f6e580f09de02b84029652e21e56f",
    "title": "Cơ cấu danh mục ra sao khi thị trường biến động mạnh?",
    "link": "https://vnexpress.net/co-cau-danh-muc-ra-sao-khi-thi-truong-bien-dong-manh-5049682.html",
    "summary": "Giữa những lúc thị trường rung lắc, bạn có biết cách cơ cấu danh mục cổ phiếu để giảm rủi ro mà vẫn giữ cơ hội tăng trưởng?",
    "source": "VnExpress - Kinh Doanh",
    "category": "Kinh doanh",
    "published": "2026-03-15T21:00:00+07:00",
    "fetched": "2026-03-17T01:49:13.655359+07:00"
  },
  {
    "id": "a0aaae0d9235a1426507688f27f2aab6",
    "title": "Meta có thể sa thải nhân viên quy mô lớn vì AI",
    "link": "https://vnexpress.net/meta-co-the-sa-thai-nhan-vien-quy-mo-lon-vi-ai-5050671.html",
    "summary": "Meta cân nhắc cắt giảm lượng lớn nhân sự trong bối cảnh chi phí đầu tư hạ tầng AI tăng mạnh.",
    "source": "VnExpress - Công Nghệ",
    "category": "Công nghệ",
    "published": "2026-03-15T12:00:00+07:00",
    "fetched": "2026-03-17T01:49:16.361368+07:00"
  },
  {
    "id": "95059f11b12d8db12038fa3bebade2db",
    "title": "Những tính năng có thể trang bị trên iPhone gập",
    "link": "https://vnexpress.net/nhung-tinh-nang-co-the-trang-bi-tren-iphone-gap-5049838.html",
    "summary": "Mẫu iPhone màn hình gập đầu tiên của Apple có thể mang tên Ultra, dùng chip 2 nm, bản lề kim loại lỏng và giá gần 3.000 USD.",
    "source": "VnExpress - Công Nghệ",
    "category": "Công nghệ",
    "published": "2026-03-15T11:00:00+07:00",
    "fetched": "2026-03-17T01:49:16.361038+07:00"
  },
  {
    "id": "3de13ab7d890aaf171a31bcc73b65f52",
    "title": "Bạn biết gì về 'đội quân vệ tinh' quanh Trái Đất?",
    "link": "https://vnexpress.net/ban-biet-gi-ve-doi-quan-ve-tinh-quanh-trai-dat-5050658.html",
    "summary": "Hàng nghìn vệ tinh quay quanh Trái Đất, giúp định vị, chụp ảnh, cung cấp Internet và dự báo thời tiết. Bạn hiểu \"đội quân\" này đến đâu?",
    "source": "VnExpress - Công Nghệ",
    "category": "Công nghệ",
    "published": "2026-03-15T09:13:38+07:00",
    "fetched": "2026-03-17T01:49:16.361519+07:00"
  },
  {
    "id": "d0b99c872c06a4dfd799df63ae0f5f88",
    "title": "Ông chủ ChatGPT: AI đang trở thành 'vật tế' cho sa thải",
    "link": "https://vnexpress.net/ong-chu-chatgpt-ai-dang-tro-thanh-vat-te-cho-sa-thai-5050323.html",
    "summary": "CEO OpenAI Sam Altman cho rằng AI đang trở thành \"vật tế\", tức là lý do cho doanh nghiệp cắt giảm nhân sự và chi phí tiện ích gia tăng.",
    "source": "VnExpress - Công Nghệ",
    "category": "Công nghệ",
    "published": "2026-03-15T00:00:00+07:00",
    "fetched": "2026-03-17T01:49:16.361216+07:00"
  }
]